sumint/__init__.py
sumint/classes.py
sumint-0.0.1.dist-info/LICENSE
sumint-0.0.1.dist-info/METADATA
sumint-0.0.1.dist-info/WHEEL
sumint-0.0.1.dist-info/top_level.txt
sumint-0.0.1.dist-info/RECORD
