Metadata-Version: 2.1
Name: sumint
Version: 0.0.1
Summary: Somador de numeros inteiros em uma lista
Author: Joao Neto
Author-email: joaonetoprivado2001@ufpi.edu.br
License: MIT License
Keywords: soma inteiros
License-File: LICENSE
